unfqt/__init__.py
unfqt/custom_indicators.py
unfqt/custom_takeprofit.py
unfqt/divergences.py
unfqt/helper_mixin.py
unfqt/helpers.py
unfqt/strat_utils.py
unfqt/version.py
unfqt/wrap_gc.py
unfqt/TechnicalAnalysisAutomation/directional_change.py
unfqt/TechnicalAnalysisAutomation/flags_pennants.py
unfqt/TechnicalAnalysisAutomation/head_shoulders.py
unfqt/TechnicalAnalysisAutomation/perceptually_important.py
unfqt/TechnicalAnalysisAutomation/pip_pattern_miner.py
unfqt/TechnicalAnalysisAutomation/rolling_window.py
unfqt/TechnicalAnalysisAutomation/test_flag_patterns.py
unfqt/TechnicalAnalysisAutomation/test_hs_patterns.py
unfqt/TechnicalAnalysisAutomation/trendline_automation.py
unfqt/TechnicalAnalysisAutomation/wf_pip_miner.py
unfqt-0.2.3.dist-info/METADATA
unfqt-0.2.3.dist-info/WHEEL
unfqt-0.2.3.dist-info/top_level.txt
unfqt-0.2.3.dist-info/RECORD
